rcnb/__init__.py
rcnb/core.py
rcnb-1.0.1.dist-info/LICENSE
rcnb-1.0.1.dist-info/METADATA
rcnb-1.0.1.dist-info/WHEEL
rcnb-1.0.1.dist-info/top_level.txt
rcnb-1.0.1.dist-info/RECORD
