Metadata-Version: 2.1
Name: rcnb
Version: 1.0.1
Summary: Everything can be encoded into RCNB with Python
Home-page: https://github.com/chr233/RCNB.python
Author: chr_
Author-email: chr@chrxw.com
License: UNKNOWN
Platform: UNKNOWN
Classifier: Programming Language :: Python :: 3 :: Only
Classifier: License :: OSI Approved :: GNU Affero General Public License v3 or later (AGPLv3+)
Classifier: Operating System :: OS Independent
Requires-Python: >=3.0
